odoo/addons/sale_elaboration/README.rst
odoo/addons/sale_elaboration/__init__.py
odoo/addons/sale_elaboration/__manifest__.py
odoo/addons/sale_elaboration/i18n/de.po
odoo/addons/sale_elaboration/i18n/es.po
odoo/addons/sale_elaboration/i18n/sale_elaboration.pot
odoo/addons/sale_elaboration/models/__init__.py
odoo/addons/sale_elaboration/models/product.py
odoo/addons/sale_elaboration/models/product_elaboration.py
odoo/addons/sale_elaboration/models/sale_order.py
odoo/addons/sale_elaboration/models/stock_picking.py
odoo/addons/sale_elaboration/readme/CONFIGURE.rst
odoo/addons/sale_elaboration/readme/CONTRIBUTORS.rst
odoo/addons/sale_elaboration/readme/DESCRIPTION.rst
odoo/addons/sale_elaboration/readme/USAGE.rst
odoo/addons/sale_elaboration/reports/report_deliveryslip.xml
odoo/addons/sale_elaboration/security/ir.model.access.csv
odoo/addons/sale_elaboration/static/description/icon.png
odoo/addons/sale_elaboration/static/description/index.html
odoo/addons/sale_elaboration/tests/__init__.py
odoo/addons/sale_elaboration/tests/test_sale_elaboration.py
odoo/addons/sale_elaboration/views/product_views.xml
odoo/addons/sale_elaboration/views/sale_elaboration_report_views.xml
odoo/addons/sale_elaboration/views/sale_elaboration_views.xml
odoo/addons/sale_elaboration/views/sale_order_views.xml
odoo11_addon_sale_elaboration-11.0.1.1.1.dist-info/METADATA
odoo11_addon_sale_elaboration-11.0.1.1.1.dist-info/WHEEL
odoo11_addon_sale_elaboration-11.0.1.1.1.dist-info/top_level.txt
odoo11_addon_sale_elaboration-11.0.1.1.1.dist-info/RECORD
